qsarmodelingpy/Fcritico.xlsx
qsarmodelingpy/Interfaces.py
qsarmodelingpy/Utils.py
qsarmodelingpy/__init__.py
qsarmodelingpy/calculate_parameters.py
qsarmodelingpy/cross_validation_class.py
qsarmodelingpy/external_validation.py
qsarmodelingpy/filter.py
qsarmodelingpy/ga.py
qsarmodelingpy/kennardstonealgorithm.py
qsarmodelingpy/leaveNout.py
qsarmodelingpy/lj_cut.py
qsarmodelingpy/lno.py
qsarmodelingpy/ops.py
qsarmodelingpy/outlier.py
qsarmodelingpy/plsbdg.py
qsarmodelingpy/runExtVal.py
qsarmodelingpy/runGa.py
qsarmodelingpy/runOPS.py
qsarmodelingpy/save_PLS_coefficients.py
qsarmodelingpy/systematic_search.py
qsarmodelingpy/validate_yr_lno.py
qsarmodelingpy/validate_yr_lno_ext.py
qsarmodelingpy/yrandomization.py
qsarmodelingpy-0.3.1.dist-info/LICENSE
qsarmodelingpy-0.3.1.dist-info/METADATA
qsarmodelingpy-0.3.1.dist-info/WHEEL
qsarmodelingpy-0.3.1.dist-info/top_level.txt
qsarmodelingpy-0.3.1.dist-info/RECORD
