Metadata-Version: 2.1
Name: qsarmodelingpy
Version: 0.3.1
Summary: A package for building and validating QSAR models
Home-page: https://github.com/hellmrf/QSARModelingPy
Author: Martins, J. P. A; Reis Filho, H. M.
Author-email: jpam@qui.ufmg.br,helitonmrf@ufmg.br
License: UNKNOWN
Platform: UNKNOWN
Classifier: Programming Language :: Python :: 3
Classifier: Operating System :: OS Independent
Requires-Python: >=3.6
License-File: LICENSE
Requires-Dist: numpy (>=1.20.1)
Requires-Dist: pandas (>=1.2.2)
Requires-Dist: scikit-learn (>=0.21.1)
Requires-Dist: deap (>=1.3.1)
Requires-Dist: tqdm (>=4.59.0)
